infovar/__init__.py
infovar/handlers/__init__.py
infovar/handlers/continuous_handler.py
infovar/handlers/discrete_handler.py
infovar/handlers/getters.py
infovar/handlers/handler.py
infovar/processing/__init__.py
infovar/processing/continuous_helper.py
infovar/stats/__init__.py
infovar/stats/canonical_estimators.py
infovar/stats/entropy_estimators.py
infovar/stats/info_theory.py
infovar/stats/preprocessing.py
infovar/stats/ranking.py
infovar/stats/resampling.py
infovar/stats/statistics.py
infovar-0.2.0.dist-info/LICENSE
infovar-0.2.0.dist-info/METADATA
infovar-0.2.0.dist-info/WHEEL
infovar-0.2.0.dist-info/RECORD
