Metadata-Version: 2.1
Name: infovar
Version: 0.2.0
Summary: Informative variables (InfoVar)
Home-page: https://github.com/einigl/infovar
Keywords: statistics,information theory
Author: Lucas Einig
Requires-Python: >=3.9
Classifier: License :: OSI Approved :: MIT License
Classifier: Operating System :: OS Independent
Classifier: Programming Language :: Python :: 3
Classifier: Programming Language :: Python :: 3.9
Classifier: Programming Language :: Python :: 3.10
Classifier: Programming Language :: Python :: 3.11
Classifier: Programming Language :: Python :: 3.12
Requires-Dist: jupyter (>=1.0.0,<2.0.0)
Requires-Dist: matplotlib (>=3.5)
Requires-Dist: notebook (>=6.4)
Requires-Dist: numpy (>=1.20)
Requires-Dist: scikit-learn (>=1.1)
Requires-Dist: scipy (>=1.10)
Requires-Dist: tqdm (>=4.66.3)
Project-URL: Bug Tracker, https://github.com/einigl/infovar/issues
Project-URL: Repository, https://github.com/einigl/infovar
